[
null,
{"id":1,"animationId":0,"consumable":false,"damage":{"critical":false,"elementId":0,"formula":"0","type":0,"variance":20},"description":"A key that opens a door.","effects":[],"hitType":0,"iconIndex":195,"itypeId":2,"name":"Small Key","note":"","occasion":3,"price":0,"repeats":1,"scope":0,"speed":0,"successRate":100,"tpGain":0},
{"id":2,"animationId":0,"consumable":true,"damage":{"critical":false,"elementId":0,"formula":"0","type":0,"variance":20},"description":"A meal made with love and a lot of cheese.","effects":[{"code":11,"dataId":0,"value1":1,"value2":0},{"code":12,"dataId":0,"value1":1,"value2":0},{"code":21,"dataId":15,"value1":1,"value2":0},{"code":22,"dataId":9,"value1":1,"value2":0}],"hitType":0,"iconIndex":274,"itypeId":1,"name":"Abby's Breakfast","note":"","occasion":1,"price":0,"repeats":1,"scope":7,"speed":0,"successRate":100,"tpGain":0},
{"id":3,"animationId":0,"consumable":true,"damage":{"critical":false,"elementId":0,"formula":"0","type":0,"variance":20},"description":"Heal 25 HP.","effects":[{"code":11,"dataId":0,"value1":0,"value2":25}],"hitType":0,"iconIndex":266,"itypeId":1,"name":"Bread","note":"","occasion":0,"price":0,"repeats":1,"scope":7,"speed":0,"successRate":100,"tpGain":0},
{"id":4,"animationId":0,"consumable":true,"damage":{"critical":false,"elementId":0,"formula":"0","type":0,"variance":20},"description":"Heal 50 HP.","effects":[{"code":11,"dataId":0,"value1":0,"value2":50}],"hitType":0,"iconIndex":269,"itypeId":1,"name":"Cheese","note":"","occasion":0,"price":0,"repeats":1,"scope":7,"speed":0,"successRate":100,"tpGain":0},
{"id":5,"animationId":0,"consumable":true,"damage":{"critical":false,"elementId":0,"formula":"0","type":0,"variance":20},"description":"Heal 35% of HP.","effects":[{"code":11,"dataId":0,"value1":0.35,"value2":0}],"hitType":0,"iconIndex":228,"itypeId":1,"name":"Lesser Potion of Health","note":"","occasion":0,"price":0,"repeats":1,"scope":7,"speed":0,"successRate":100,"tpGain":0},
{"id":6,"animationId":0,"consumable":true,"damage":{"critical":false,"elementId":0,"formula":"0","type":0,"variance":20},"description":"Heal 45% of HP.","effects":[{"code":11,"dataId":0,"value1":0.45,"value2":0}],"hitType":0,"iconIndex":228,"itypeId":1,"name":"Greater Potion of Health","note":"","occasion":0,"price":0,"repeats":1,"scope":7,"speed":0,"successRate":100,"tpGain":0},
{"id":7,"animationId":0,"consumable":true,"damage":{"critical":false,"elementId":0,"formula":"0","type":0,"variance":20},"description":"Recover 35 MP.","effects":[{"code":12,"dataId":0,"value1":0,"value2":35}],"hitType":0,"iconIndex":176,"itypeId":1,"name":"Apple Juice","note":"","occasion":0,"price":0,"repeats":1,"scope":7,"speed":0,"successRate":100,"tpGain":0},
{"id":8,"animationId":0,"consumable":true,"damage":{"critical":false,"elementId":0,"formula":"0","type":0,"variance":20},"description":"Recover 70 MP.","effects":[{"code":12,"dataId":0,"value1":0,"value2":70}],"hitType":0,"iconIndex":176,"itypeId":1,"name":"Orange Juice","note":"","occasion":0,"price":0,"repeats":1,"scope":7,"speed":0,"successRate":100,"tpGain":0},
{"id":9,"animationId":0,"consumable":true,"damage":{"critical":false,"elementId":0,"formula":"0","type":0,"variance":20},"description":"Recover 115 MP.","effects":[{"code":12,"dataId":0,"value1":0,"value2":115}],"hitType":0,"iconIndex":176,"itypeId":1,"name":"Grape Juice","note":"","occasion":0,"price":0,"repeats":1,"scope":7,"speed":0,"successRate":100,"tpGain":0},
{"id":10,"animationId":0,"consumable":true,"damage":{"critical":false,"elementId":0,"formula":"0","type":0,"variance":20},"description":"Gel of a blue slime.","effects":[{"code":12,"dataId":0,"value1":0.05,"value2":0},{"code":11,"dataId":0,"value1":0,"value2":12}],"hitType":0,"iconIndex":165,"itypeId":1,"name":"Blue Gel","note":"","occasion":0,"price":0,"repeats":1,"scope":7,"speed":0,"successRate":100,"tpGain":0},
{"id":11,"animationId":0,"consumable":true,"damage":{"critical":false,"elementId":0,"formula":"0","type":0,"variance":20},"description":"Gel of a red slime.","effects":[{"code":12,"dataId":0,"value1":0.1,"value2":0},{"code":11,"dataId":0,"value1":0,"value2":12}],"hitType":0,"iconIndex":162,"itypeId":1,"name":"Red Gel","note":"","occasion":0,"price":0,"repeats":1,"scope":7,"speed":0,"successRate":100,"tpGain":0},
{"id":12,"animationId":0,"consumable":true,"damage":{"critical":false,"elementId":0,"formula":"0","type":0,"variance":20},"description":"Gel of a green slime.","effects":[{"code":12,"dataId":0,"value1":0.05,"value2":0},{"code":11,"dataId":0,"value1":0.05,"value2":12}],"hitType":0,"iconIndex":164,"itypeId":1,"name":"Green Gel","note":"","occasion":0,"price":0,"repeats":1,"scope":7,"speed":0,"successRate":100,"tpGain":0},
{"id":13,"animationId":0,"consumable":true,"damage":{"critical":false,"elementId":0,"formula":"0","type":0,"variance":20},"description":"Gel of a purple slime...","effects":[{"code":12,"dataId":0,"value1":0.1,"value2":12},{"code":11,"dataId":0,"value1":0.08,"value2":24}],"hitType":0,"iconIndex":302,"itypeId":1,"name":"Purple Gel","note":"","occasion":0,"price":0,"repeats":1,"scope":7,"speed":0,"successRate":100,"tpGain":0},
{"id":14,"animationId":0,"consumable":true,"damage":{"critical":false,"elementId":0,"formula":"0","type":0,"variance":20},"description":"Gel of a golden slime...","effects":[{"code":12,"dataId":0,"value1":0.1,"value2":120},{"code":11,"dataId":0,"value1":0.08,"value2":240}],"hitType":0,"iconIndex":163,"itypeId":1,"name":"Golden Gel","note":"","occasion":0,"price":0,"repeats":1,"scope":7,"speed":0,"successRate":100,"tpGain":0},
{"id":15,"animationId":0,"consumable":false,"damage":{"critical":false,"elementId":0,"formula":"0","type":0,"variance":20},"description":"UNIV_COMM_2184_ITEM_DESC","effects":[{"code":44,"dataId":3,"value1":1,"value2":0}],"hitType":0,"iconIndex":201,"itypeId":2,"name":"100010001000","note":"","occasion":2,"price":0,"repeats":1,"scope":7,"speed":0,"successRate":100,"tpGain":0},
{"id":16,"animationId":0,"consumable":true,"damage":{"critical":false,"elementId":0,"formula":"50","type":3,"variance":20},"description":"Undo most negative status effects.","effects":[{"code":22,"dataId":16,"value1":0.85,"value2":0},{"code":22,"dataId":4,"value1":0.85,"value2":0},{"code":22,"dataId":10,"value1":0.85,"value2":0},{"code":22,"dataId":12,"value1":0.85,"value2":0},{"code":22,"dataId":8,"value1":0.85,"value2":0},{"code":22,"dataId":13,"value1":0.85,"value2":0}],"hitType":0,"iconIndex":196,"itypeId":1,"name":"Cookie","note":"","occasion":0,"price":0,"repeats":1,"scope":7,"speed":0,"successRate":100,"tpGain":0},
{"id":17,"animationId":0,"consumable":true,"damage":{"critical":false,"elementId":0,"formula":"0","type":0,"variance":20},"description":"Heal 50% of HP.","effects":[{"code":11,"dataId":0,"value1":0.5,"value2":0}],"hitType":0,"iconIndex":228,"itypeId":1,"name":"[Cr] Potion of Health","note":"","occasion":0,"price":0,"repeats":1,"scope":7,"speed":0,"successRate":100,"tpGain":0},
{"id":18,"animationId":0,"consumable":true,"damage":{"critical":false,"elementId":0,"formula":"0","type":0,"variance":20},"description":"Heal 50% of MP.","effects":[{"code":12,"dataId":0,"value1":0.5,"value2":0}],"hitType":0,"iconIndex":228,"itypeId":1,"name":"[Cr] Potion of Mana","note":"","occasion":0,"price":0,"repeats":1,"scope":7,"speed":0,"successRate":100,"tpGain":0},
{"id":19,"animationId":0,"consumable":true,"damage":{"critical":false,"elementId":0,"formula":"0","type":0,"variance":20},"description":"Makes a person hyper-aware.","effects":[{"code":21,"dataId":14,"value1":1,"value2":0}],"hitType":0,"iconIndex":226,"itypeId":1,"name":"[Cr] Hyper Potion","note":"","occasion":0,"price":0,"repeats":1,"scope":7,"speed":0,"successRate":100,"tpGain":0},
{"id":20,"animationId":0,"consumable":false,"damage":{"critical":false,"elementId":0,"formula":"0","type":0,"variance":20},"description":"Key to a door in the mansion.","effects":[],"hitType":0,"iconIndex":109,"itypeId":2,"name":"Mansion Key","note":"","occasion":3,"price":0,"repeats":1,"scope":0,"speed":0,"successRate":100,"tpGain":0},
{"id":21,"animationId":0,"consumable":false,"damage":{"critical":false,"elementId":0,"formula":"0","type":0,"variance":20},"description":"Key to the temple.","effects":[],"hitType":0,"iconIndex":108,"itypeId":2,"name":"Temple Key","note":"","occasion":3,"price":0,"repeats":1,"scope":0,"speed":0,"successRate":100,"tpGain":0},
{"id":22,"animationId":0,"consumable":true,"damage":{"critical":false,"elementId":0,"formula":"0","type":0,"variance":20},"description":"","effects":[],"hitType":0,"iconIndex":0,"itypeId":1,"name":"","note":"","occasion":0,"price":0,"repeats":1,"scope":7,"speed":0,"successRate":100,"tpGain":0},
{"id":23,"animationId":0,"consumable":true,"damage":{"critical":false,"elementId":0,"formula":"0","type":0,"variance":20},"description":"","effects":[],"hitType":0,"iconIndex":0,"itypeId":1,"name":"","note":"","occasion":0,"price":0,"repeats":1,"scope":7,"speed":0,"successRate":100,"tpGain":0},
{"id":24,"animationId":0,"consumable":true,"damage":{"critical":false,"elementId":0,"formula":"0","type":0,"variance":20},"description":"","effects":[],"hitType":0,"iconIndex":0,"itypeId":1,"name":"","note":"","occasion":0,"price":0,"repeats":1,"scope":7,"speed":0,"successRate":100,"tpGain":0},
{"id":25,"animationId":0,"consumable":true,"damage":{"critical":false,"elementId":0,"formula":"0","type":0,"variance":20},"description":"","effects":[],"hitType":0,"iconIndex":0,"itypeId":1,"name":"","note":"","occasion":0,"price":0,"repeats":1,"scope":7,"speed":0,"successRate":100,"tpGain":0},
{"id":26,"animationId":0,"consumable":true,"damage":{"critical":false,"elementId":0,"formula":"0","type":0,"variance":20},"description":"","effects":[],"hitType":0,"iconIndex":0,"itypeId":1,"name":"","note":"","occasion":0,"price":0,"repeats":1,"scope":7,"speed":0,"successRate":100,"tpGain":0},
{"id":27,"animationId":0,"consumable":true,"damage":{"critical":false,"elementId":0,"formula":"0","type":0,"variance":20},"description":"","effects":[],"hitType":0,"iconIndex":0,"itypeId":1,"name":"","note":"","occasion":0,"price":0,"repeats":1,"scope":7,"speed":0,"successRate":100,"tpGain":0},
{"id":28,"animationId":0,"consumable":true,"damage":{"critical":false,"elementId":0,"formula":"0","type":0,"variance":20},"description":"","effects":[],"hitType":0,"iconIndex":0,"itypeId":1,"name":"","note":"","occasion":0,"price":0,"repeats":1,"scope":7,"speed":0,"successRate":100,"tpGain":0},
{"id":29,"animationId":0,"consumable":true,"damage":{"critical":false,"elementId":0,"formula":"0","type":0,"variance":20},"description":"","effects":[],"hitType":0,"iconIndex":0,"itypeId":1,"name":"","note":"","occasion":0,"price":0,"repeats":1,"scope":7,"speed":0,"successRate":100,"tpGain":0},
{"id":30,"animationId":0,"consumable":true,"damage":{"critical":false,"elementId":0,"formula":"0","type":0,"variance":20},"description":"","effects":[],"hitType":0,"iconIndex":0,"itypeId":1,"name":"","note":"","occasion":0,"price":0,"repeats":1,"scope":7,"speed":0,"successRate":100,"tpGain":0},
{"id":31,"animationId":0,"consumable":true,"damage":{"critical":false,"elementId":0,"formula":"0","type":0,"variance":20},"description":"","effects":[],"hitType":0,"iconIndex":0,"itypeId":1,"name":"","note":"","occasion":0,"price":0,"repeats":1,"scope":7,"speed":0,"successRate":100,"tpGain":0},
{"id":32,"animationId":0,"consumable":true,"damage":{"critical":false,"elementId":0,"formula":"0","type":0,"variance":20},"description":"","effects":[],"hitType":0,"iconIndex":0,"itypeId":1,"name":"","note":"","occasion":0,"price":0,"repeats":1,"scope":7,"speed":0,"successRate":100,"tpGain":0},
{"id":33,"animationId":0,"consumable":true,"damage":{"critical":false,"elementId":0,"formula":"0","type":0,"variance":20},"description":"","effects":[],"hitType":0,"iconIndex":0,"itypeId":1,"name":"","note":"","occasion":0,"price":0,"repeats":1,"scope":7,"speed":0,"successRate":100,"tpGain":0},
{"id":34,"animationId":0,"consumable":true,"damage":{"critical":false,"elementId":0,"formula":"0","type":0,"variance":20},"description":"","effects":[],"hitType":0,"iconIndex":0,"itypeId":1,"name":"","note":"","occasion":0,"price":0,"repeats":1,"scope":7,"speed":0,"successRate":100,"tpGain":0},
{"id":35,"animationId":0,"consumable":true,"damage":{"critical":false,"elementId":0,"formula":"0","type":0,"variance":20},"description":"","effects":[],"hitType":0,"iconIndex":0,"itypeId":1,"name":"","note":"","occasion":0,"price":0,"repeats":1,"scope":7,"speed":0,"successRate":100,"tpGain":0}
]